[
  {
    "lectureNumber": 1,
    "lectureName": "Cell Cycle and Cell Division 08 : G0 ...",
    "lectureCode": "eb3ab0da-d00d-4447-a607-ab6f48f58e24",
    "extId": "650e0997cd96be0018864127",
    "key": "650edbd2eba48400181a87ce",
    "classNotesCode": "dde56b86-93d8-495c-ad35-582363eda686.pdf",
    "dppsPdfCode": "289d1333-91a1-4666-afa1-649852adadee.pdf",
    "dppsSolutionCode": ""
  },
  {
    "lectureNumber": 2,
    "lectureName": "Cell Cycle and Cell Division 07 : Mei...",
    "lectureCode": "2261acb2-c99d-4fcb-876d-2f56391e17f5",
    "extId": "650a12c796f81d0019184baf",
    "key": "650ae7197f8660001890873c",
    "classNotesCode": "e4a8de3c-57dd-4e07-bc44-89828067d85e.pdf",
    "dppsPdfCode": "9c669c11-d170-4798-b2cf-f2a305e51942.pdf",
    "dppsSolutionCode": ""
  },
  {
    "lectureNumber": 3,
    "lectureName": "Cell Cycle and Cell Division 06 : Mei...",
    "lectureCode": "d9626381-4686-4230-89f9-b00574cbfd3a",
    "extId": "6504b838c96e400018e4b8b3",
    "key": "6505a09f39aac10018151e34",
    "classNotesCode": "4a1ec89b-5161-4c8a-9eba-88d59f95c7a0.pdf",
    "dppsPdfCode": "dc266645-2a60-4bd3-b0d5-d8e91eb989d8.pdf",
    "dppsSolutionCode": ""
  },
  {
    "lectureNumber": 4,
    "lectureName": "Cell Cycle and Cell Division 05 : Cel...",
    "lectureCode": "526c3752-f5db-4186-bc94-2e4b0fc7b49d",
    "extId": "6500bf4e42500700180a4513",
    "key": "6501ae303105d2001291e9e8",
    "classNotesCode": "c5919ce2-7208-4d7f-88ed-3e5d16421db2.pdf",
    "dppsPdfCode": "4f109841-b8ac-409f-b10b-50a3ef9dcbbb.pdf",
    "dppsSolutionCode": ""
  },
  {
    "lectureNumber": 5,
    "lectureName": "Cell Cycle and Cell Division 04 : Met...",
    "lectureCode": "4fe5b4c9-97cf-4b71-b304-a1bcc73ff6a4",
    "extId": "64ff6ffb2b2a660018f520d4",
    "key": "65005a7801b86900189f2322",
    "classNotesCode": "9a28ead7-c96a-4e2b-82ce-ad6ed32d5707.pdf",
    "dppsPdfCode": "bb906c2f-53c3-49f3-92f9-dfdf67f7522a.pdf",
    "dppsSolutionCode": ""
  },
  {
    "lectureNumber": 6,
    "lectureName": "Cell Cycle and Cell Division 03 : Pro...",
    "lectureCode": "65dad659-1f54-450d-b98e-c533628cbd0a",
    "extId": "64fb82f27289f90018d1e3bc",
    "key": "64fc665e0a21d300122d20a3",
    "classNotesCode": "bfe1055a-45f4-4354-b01c-1d74784a79b7.pdf",
    "dppsPdfCode": "acbb8cc9-4e82-4ae6-baaa-bab9c6972aa9.pdf",
    "dppsSolutionCode": ""
  },
  {
    "lectureNumber": 7,
    "lectureName": "Cell Cycle and Cell Division 02 : Chr...",
    "lectureCode": "9895bdcf-9426-4bc0-a6aa-68f8639ae618",
    "extId": "64f78be3d0503400181aabfe",
    "key": "64f86f9431bf160018b80c67",
    "classNotesCode": "b9c2b52d-9f79-48c6-b082-2ad9957783ef.pdf",
    "dppsPdfCode": "4c8e432d-1077-49df-b93c-8052c18a4ed3.pdf",
    "dppsSolutionCode": ""
  },
  {
    "lectureNumber": 8,
    "lectureName": "Cell Cycle and Cell Division 01 : Int...",
    "lectureCode": "dbed9e21-54db-4a66-be14-1606bf1fefb8",
    "extId": "64f299c3ea7b370018d907af",
    "key": "64f32d642448ab001882c9e4",
    "classNotesCode": "c8577111-dae9-4bb7-a8c3-56e27bc6ddd4.pdf",
    "dppsPdfCode": "77ebdfc3-cfb5-4d70-8f37-4cb9e738f2e9.pdf",
    "dppsSolutionCode": ""
  },
  {
    "lectureNumber": 9,
    "lectureName": "Cell Cycle and Cell Division Solution to DPP...",
    "lectureCode": "",
    "extId": "",
    "key": "",
    "classNotesCode": "9614b8fe-e11d-4d43-9ab4-21c16ba85a0d.pdf",
    "dppsPdfCode": "23cf00e3-52ca-42c2-97c5-75eb2facc1a7.pdf",
    "dppsSolutionCode": ""
  },
  {
    "lectureNumber": 10,
    "lectureName": "",
    "lectureCode": "",
    "extId": "",
    "key": "",
    "classNotesCode": "34da3c10-fcbb-41c1-ba29-0184720d5bda.pdf",
    "dppsPdfCode": "a8eb2deb-ab70-4e22-87fe-e41386d686a8.pdf",
    "dppsSolutionCode": ""
  },
  {
    "lectureNumber": 11,
    "lectureName": "",
    "lectureCode": "",
    "extId": "",
    "key": "",
    "classNotesCode": "dde56b86-93d8-495c-ad35-582363eda686.pdf",
    "dppsPdfCode": "5b65f600-7e3d-408e-869c-fb819ce7f527.pdf",
    "dppsSolutionCode": ""
  },
  {
    "lectureNumber": 12,
    "lectureName": "",
    "lectureCode": "",
    "extId": "",
    "key": "",
    "classNotesCode": "e4a8de3c-57dd-4e07-bc44-89828067d85e.pdf",
    "dppsPdfCode": "7a2c99e1-5bde-47c3-8d15-4307ddc9eec9.pdf",
    "dppsSolutionCode": ""
  }
]