[
  {
    "lectureNumber": 1,
    "lectureName": "Friction 03 : Friction in Pulley Prob...",
    "lectureCode": "be87010b-6eac-4003-b159-9a2f77b7171d",
    "extId": "654560db475b390018499998",
    "key": "65452f69d61bfb001899f86d",
    "classNotesCode": "6c39f121-209d-4c0d-b40d-a2279df33bc8.pdf",
    "dppsPdfCode": "4ddef880-a8cd-4601-ba2b-0dff64327a6e.pdf",
    "dppsSolutionCode": ""
  },
  {
    "lectureNumber": 2,
    "lectureName": "Friction 02 : Angle of Friction || An...",
    "lectureCode": "abd6f66c-022b-46b7-a7d4-a06be211e07b",
    "extId": "65446bd4f73bb30018bab39e",
    "key": "654502fb68ca6b0018c39779",
    "classNotesCode": "96fdc8a2-864e-451b-bc18-143a1ed16d64.pdf",
    "dppsPdfCode": "9d364317-9655-4ab2-a95a-6a4e47c00a5b.pdf",
    "dppsSolutionCode": ""
  },
  {
    "lectureNumber": 3,
    "lectureName": "Friction 01 : Frictional Force || (NO...",
    "lectureCode": "acd22655-580e-4899-823d-b166832a3a1f",
    "extId": "654319cd26c1280018982f92",
    "key": "6543b1acad6d470018485412",
    "classNotesCode": "419a4c0f-68df-40a3-9a81-c651ff2c8e6d.pdf",
    "dppsPdfCode": "",
    "dppsSolutionCode": ""
  }
]