[
  {
    "lectureNumber": 1,
    "lectureName": "Structure of Atom 02 : NCERT Discussion",
    "lectureCode": "7cce3398-cbb1-4ba2-b047-1eb6337097e6",
    "extId": "64feb276a7ce0b001887006c",
    "key": "6458906ca0ce1b0018a75a47",
    "classNotesCode": "bcfeb06f-6ae5-4deb-9444-8d0368c3af90.pdf",
    "dppsPdfCode": "",
    "dppsSolutionCode": ""
  },
  {
    "lectureNumber": 2,
    "lectureName": "Structure of Atom 01 : NCERT Discussion",
    "lectureCode": "f7db8d90-21d7-4e4d-bcd4-af757c03c62c",
    "extId": "64feb29f4142630018cc7e0f",
    "key": "64588d10388beb0018db92db",
    "classNotesCode": "0c7c9ba6-ab7f-49f4-b812-14e3670f1bc3.pdf",
    "dppsPdfCode": "",
    "dppsSolutionCode": ""
  },
  {
    "lectureNumber": 3,
    "lectureName": "Redox Reactions 01 : NCERT Back Exerc...",
    "lectureCode": "e2dee166-5d30-4be4-8473-6b883895204b",
    "extId": "64c759f616d426001838caed",
    "key": "6458b894d69d630018071f98",
    "classNotesCode": "f8733c70-143e-4146-98e1-d4da0825f53a.pdf",
    "dppsPdfCode": "",
    "dppsSolutionCode": ""
  },
  {
    "lectureNumber": 4,
    "lectureName": "Redox Reactions 01 : Theory Session*",
    "lectureCode": "d90d4db0-c493-4228-8c2c-adc2c6a97937",
    "extId": "64c759c90311200018f65ac7",
    "key": "6458b5c36bc2df0018b50fff",
    "classNotesCode": "b1b22b1d-565b-46d5-a466-6e3a276ef67e.pdf",
    "dppsPdfCode": "",
    "dppsSolutionCode": ""
  },
  {
    "lectureNumber": 5,
    "lectureName": "Chemical + Ionic Equilibrium 01 : NCE...",
    "lectureCode": "1cb6b79b-f6f5-4971-9b3e-f931254881b5",
    "extId": "64f040d76f8f5d0018e6826f",
    "key": "64632cd8c9ed530018c77060",
    "classNotesCode": "add944e6-72aa-4a1b-9c04-2c44aba96897.pdf",
    "dppsPdfCode": "",
    "dppsSolutionCode": ""
  },
  {
    "lectureNumber": 6,
    "lectureName": "Chemical + Ionic Equilibrium 02 : The...",
    "lectureCode": "6e9e5fc9-c933-4dac-8b5d-e5306d27000a",
    "extId": "64f040957dc9b700194a8215",
    "key": "64632bc7ff15cb00183b6c53",
    "classNotesCode": "1abc3028-d396-4560-b8f4-18be856f05c3.pdf",
    "dppsPdfCode": "",
    "dppsSolutionCode": ""
  },
  {
    "lectureNumber": 7,
    "lectureName": "Chemical + Ionic Equilibrium 01 : The...",
    "lectureCode": "1591668e-0a8a-4dd2-8e31-3452f02c273f",
    "extId": "64f040675b6fc10018224629",
    "key": "6458ac2484dcf000185bdb8f",
    "classNotesCode": "c639b3f5-4060-464c-aae8-f8140a53c175.pdf",
    "dppsPdfCode": "",
    "dppsSolutionCode": ""
  },
  {
    "lectureNumber": 8,
    "lectureName": "Chemical Thermodynamics 02 : Theory S...",
    "lectureCode": "c382ded6-3676-41e3-953e-0e85ad2342c1",
    "extId": "64bf832bab09990018acf377",
    "key": "64632a16e1b5bf001807f552",
    "classNotesCode": "8242e138-c9d7-4af2-939b-a52abfcc7b7b.pdf",
    "dppsPdfCode": "",
    "dppsSolutionCode": ""
  },
  {
    "lectureNumber": 9,
    "lectureName": "Chemical Thermodynamics 01 : Theory S...",
    "lectureCode": "1f5adbd8-1d4c-44f2-b1d1-5d499ec2360e",
    "extId": "64bf8233f8ea5b001858d107",
    "key": "646329b3ffaa8700186f5fe7",
    "classNotesCode": "96170c61-b876-4429-9860-222229949597.pdf",
    "dppsPdfCode": "",
    "dppsSolutionCode": ""
  },
  {
    "lectureNumber": 10,
    "lectureName": "Solid State 01 : NCERT Back Exercise ...",
    "lectureCode": "f1397f19-8321-406b-9a3e-3d3f860d9e31",
    "extId": "65081ff7fa51230018c66e1f",
    "key": "643d65210adcfb001812da29",
    "classNotesCode": "a0927680-5b27-4d05-a479-bcfcad5d82d9.pdf",
    "dppsPdfCode": "",
    "dppsSolutionCode": ""
  },
  {
    "lectureNumber": 11,
    "lectureName": "Solid State 01 : Theory Session*",
    "lectureCode": "e0af254e-66d3-479b-bb95-c97fb6d110f3",
    "extId": "65081f6a9fe04b001874f487",
    "key": "642ad8235c2ed800181173fd",
    "classNotesCode": "956aeea4-60c4-4359-9604-a772135f25a8.pdf",
    "dppsPdfCode": "",
    "dppsSolutionCode": ""
  },
  {
    "lectureNumber": 12,
    "lectureName": "d & f Blocks Elements 02 : NCERT Disc...",
    "lectureCode": "2af18014-29b4-487c-af41-0272f2a07b76",
    "extId": "66115b0084e702001810505c",
    "key": "64589c90991df500184b3568",
    "classNotesCode": "d844b612-881c-472c-981d-13a42311b461.pdf",
    "dppsPdfCode": "",
    "dppsSolutionCode": ""
  },
  {
    "lectureNumber": 13,
    "lectureName": "d & f Blocks Elements 01 : NCERT Disc...",
    "lectureCode": "ed819e6f-c176-452d-aea7-726cc019f4dc",
    "extId": "66115ab9a51d670018780f34",
    "key": "645896fadc77f600180870d0",
    "classNotesCode": "f125b276-c68c-48ab-92ca-e391592b3a53.pdf",
    "dppsPdfCode": "",
    "dppsSolutionCode": ""
  },
  {
    "lectureNumber": 14,
    "lectureName": "Haloalkanes and Haloarenes-02 : NCERT...",
    "lectureCode": "2b777347-0a93-42e4-85e0-b1131191dadc",
    "extId": "65aa3858373d9d0018261ce7",
    "key": "6458b59d1610aa00184c4131",
    "classNotesCode": "88a8b53a-7a6e-45b1-b10e-c2c3be42a733.pdf",
    "dppsPdfCode": "",
    "dppsSolutionCode": ""
  },
  {
    "lectureNumber": 15,
    "lectureName": "Haloalkanes And Haloarenes-01 : NCERT...",
    "lectureCode": "c20cd152-6d1f-4aa2-a66d-9a8bb2ac40ed",
    "extId": "65aa380297102f0018873997",
    "key": "6458b2e7c71b5200181f0858",
    "classNotesCode": "abcdc88e-4a75-48c1-8632-5279f1a8c128.pdf",
    "dppsPdfCode": "",
    "dppsSolutionCode": ""
  },
  {
    "lectureNumber": 16,
    "lectureName": "Ecosystem-01 :  Theory Session*",
    "lectureCode": "c9188c63-8d95-49b6-9a99-d6525ab59e72",
    "extId": "655faf9425e8230018f082ae",
    "key": "6458be78a2e6e20018fb77d4",
    "classNotesCode": "d9c53342-a2d2-4b0a-aef2-192cad9a2ccf.pdf",
    "dppsPdfCode": "",
    "dppsSolutionCode": ""
  },
  {
    "lectureNumber": 17,
    "lectureName": "Organisms and Population - 01 : NCERT...",
    "lectureCode": "a4a5bf40-3197-4c21-8c55-2cd941882433",
    "extId": "655607c4f57ae200182d35de",
    "key": "6458c7e1108f1300185f4cbd",
    "classNotesCode": "03164223-4372-44c9-bd57-4faeccb7cd3f.pdf",
    "dppsPdfCode": "",
    "dppsSolutionCode": ""
  },
  {
    "lectureNumber": 18,
    "lectureName": "Organisms and Population - 01 : Theor...",
    "lectureCode": "30ee28a2-d44f-49db-b30f-02e356f83432",
    "extId": "65560739f56cad0018308470",
    "key": "6458c6f0c2ebc80018533f6e",
    "classNotesCode": "e502f477-791d-4852-ae00-7e0bed7575de.pdf",
    "dppsPdfCode": "",
    "dppsSolutionCode": ""
  },
  {
    "lectureNumber": 19,
    "lectureName": "plant kingdom ncert (rishabh sir)",
    "lectureCode": "b149df43-06a3-4d6e-8cc5-d565d645c9d1",
    "extId": "64ddf9c34b961600187433a5",
    "key": "64ddc596f186070018a62aff",
    "classNotesCode": "f1af0362-215a-4e8a-b012-bed37d10b0c4.pdf",
    "dppsPdfCode": "",
    "dppsSolutionCode": ""
  },
  {
    "lectureNumber": 20,
    "lectureName": "Biomolecules-01 : NCERT Back Exercise...",
    "lectureCode": "218c372f-50f1-47a3-8f04-45d301025a70",
    "extId": "6576de4c1f6c2700180d8a6e",
    "key": "6458ba7c6bc2df0018b514f9",
    "classNotesCode": "152eb5e5-1243-4dc2-a84c-2ef8f8390b89.pdf",
    "dppsPdfCode": "",
    "dppsSolutionCode": ""
  },
  {
    "lectureNumber": 21,
    "lectureName": "Structural organization in animals-01...",
    "lectureCode": "5ce474e4-f24c-478b-8dc2-d29223889581",
    "extId": "647ef53ccb1d0c0019d55011",
    "key": "6458bf261610aa00184c6b72",
    "classNotesCode": "49403aba-3883-45cc-a064-3b500e4d8a39.pdf",
    "dppsPdfCode": "",
    "dppsSolutionCode": ""
  },
  {
    "lectureNumber": 22,
    "lectureName": "Structural organization in animals-01...",
    "lectureCode": "10246dcd-fa4f-4509-a64f-e0458d3cae73",
    "extId": "647ddc32d900730018855071",
    "key": "6458ae2b108f1300185e30a7",
    "classNotesCode": "0cd65f84-c98d-487f-96d1-4f84076b10d1.pdf",
    "dppsPdfCode": "",
    "dppsSolutionCode": ""
  },
  {
    "lectureNumber": 23,
    "lectureName": "Electrochemistry-01 : NCERT Back Exer...",
    "lectureCode": "c86940e2-a383-4972-869c-d2720fe257a6",
    "extId": "64d356ed9bafa30018e3dd92",
    "key": "64588bccdc77f6001808645e",
    "classNotesCode": "1242a01d-3425-482c-b398-df6d17dd011b.pdf",
    "dppsPdfCode": "",
    "dppsSolutionCode": ""
  },
  {
    "lectureNumber": 24,
    "lectureName": "Electrochemistry 01 : Theory Session*",
    "lectureCode": "45e63a6e-9352-42ce-9fe3-0188d09d00a5",
    "extId": "64d356c2b57b5d00195b7cf8",
    "key": "64635ad2e386f0001820639d",
    "classNotesCode": "c60f72f8-a110-497e-9b45-24be49d83f3a.pdf",
    "dppsPdfCode": "",
    "dppsSolutionCode": ""
  },
  {
    "lectureNumber": 25,
    "lectureName": "Chemical Kinetics-01 : NCERT Back Exe...",
    "lectureCode": "919cc367-47c9-43da-ae22-ff520ece719c",
    "extId": "64a8f9b19ac19a0018e152ca",
    "key": "6458934d786fc600182ec21e",
    "classNotesCode": "2f154c6a-3c16-422f-af22-d30f7fa18835.pdf",
    "dppsPdfCode": "",
    "dppsSolutionCode": ""
  },
  {
    "lectureNumber": 26,
    "lectureName": "Chemical Kinetics-01 : Theory Session*",
    "lectureCode": "6a3a06c9-66cf-4d1a-b4cf-665c50a253e1",
    "extId": "64a8f930f81b7000183ffd52",
    "key": "64588ee7ef75410018c895a6",
    "classNotesCode": "4870b015-bc3e-4b05-9757-b2b15251f67b.pdf",
    "dppsPdfCode": "",
    "dppsSolutionCode": ""
  },
  {
    "lectureNumber": 27,
    "lectureName": "Solutions 02 : Theory Session and NCE...",
    "lectureCode": "77abaebe-0cfc-4354-9195-1cf3b7cd2d6f",
    "extId": "648ff5697f977c00188e0212",
    "key": "646343885b64750018ed9a2f",
    "classNotesCode": "03a846a1-d6a8-4b24-949c-0c468faa33e5.pdf",
    "dppsPdfCode": "",
    "dppsSolutionCode": ""
  },
  {
    "lectureNumber": 28,
    "lectureName": "Solutions 01 : Theory Session*",
    "lectureCode": "161b106f-7c85-4c96-b53e-3efeef0dd8e8",
    "extId": "648ff50a2b01bc00185b4051",
    "key": "64634073d31fa90018dd92aa",
    "classNotesCode": "03164223-4372-44c9-bd57-4faeccb7cd3f.pdf",
    "dppsPdfCode": "",
    "dppsSolutionCode": ""
  },
  {
    "lectureNumber": 29,
    "lectureName": "Molecular Basis of Inheritance - 01 :...",
    "lectureCode": "305904ff-f615-4918-b58a-08d0490b3aaa",
    "extId": "6590150e4e52c900199d40eb",
    "key": "6458c468991df500184c217e",
    "classNotesCode": "e502f477-791d-4852-ae00-7e0bed7575de.pdf",
    "dppsPdfCode": "",
    "dppsSolutionCode": ""
  },
  {
    "lectureNumber": 30,
    "lectureName": "Molecular Basis of Inheritance - 01 :...",
    "lectureCode": "e5a995f5-58c8-44c8-9d6c-c9d343218b2f",
    "extId": "659014d0d754f90018cd2e38",
    "key": "6458c382108f1300185f2f14",
    "classNotesCode": "f1af0362-215a-4e8a-b012-bed37d10b0c4.pdf",
    "dppsPdfCode": "",
    "dppsSolutionCode": ""
  },
  {
    "lectureNumber": 31,
    "lectureName": "States of Matters 01 : NCERT Back Exe...",
    "lectureCode": "88952d2d-c9ce-4b74-ae46-7739bde10a8b",
    "extId": "649bbc7f816cb0001835ddd1",
    "key": "649c433c307ff70018f2081b",
    "classNotesCode": "152eb5e5-1243-4dc2-a84c-2ef8f8390b89.pdf",
    "dppsPdfCode": "",
    "dppsSolutionCode": ""
  },
  {
    "lectureNumber": 32,
    "lectureName": "Biotechnology: principles and process...",
    "lectureCode": "0cc92699-7ef1-4f6e-868b-79bfaf3da7dc",
    "extId": "658bc224eeb9040018d99918",
    "key": "6458b651413a2600184418b8",
    "classNotesCode": "49403aba-3883-45cc-a064-3b500e4d8a39.pdf",
    "dppsPdfCode": "",
    "dppsSolutionCode": ""
  },
  {
    "lectureNumber": 33,
    "lectureName": "Biotechnology: principles and process...",
    "lectureCode": "d4c3d2b4-9e20-4351-a1a5-3e2608912d0e",
    "extId": "658bc193ea3eb80018d7a733",
    "key": "6458c1450c89790018b68a39",
    "classNotesCode": "0cd65f84-c98d-487f-96d1-4f84076b10d1.pdf",
    "dppsPdfCode": "",
    "dppsSolutionCode": ""
  },
  {
    "lectureNumber": 34,
    "lectureName": "Biotechnology: principles and process...",
    "lectureCode": "9f7dd4d4-311d-4af2-a18e-18b0c0728769",
    "extId": "658bc140d5dfb0001885f698",
    "key": "6458b7530c89790018b635f8",
    "classNotesCode": "1242a01d-3425-482c-b398-df6d17dd011b.pdf",
    "dppsPdfCode": "",
    "dppsSolutionCode": ""
  },
  {
    "lectureNumber": 35,
    "lectureName": "Coordination Compounds : NCERT Discus...",
    "lectureCode": "ddd4aade-17be-41cf-8b30-328f6c471f1e",
    "extId": "65edfc8e28e1090018759bda",
    "key": "6549dc805f6d7b001809c4f3",
    "classNotesCode": "c60f72f8-a110-497e-9b45-24be49d83f3a.pdf",
    "dppsPdfCode": "",
    "dppsSolutionCode": ""
  },
  {
    "lectureNumber": 36,
    "lectureName": "Coordination Compounds-01 : NCERT Dis...",
    "lectureCode": "45ac9279-a054-4ef1-84f9-d71da60d8b8e",
    "extId": "65edfc2cdd23630018b738bd",
    "key": "645cce254c7fe90018fb52a1",
    "classNotesCode": "2f154c6a-3c16-422f-af22-d30f7fa18835.pdf",
    "dppsPdfCode": "",
    "dppsSolutionCode": ""
  },
  {
    "lectureNumber": 37,
    "lectureName": "Hydrocarbons 01 : Theory Session*",
    "lectureCode": "6f0bc1f3-97b6-4a54-8406-0902caae887a",
    "extId": "65a25cdf8a65a400183c7946",
    "key": "6458c0fbd69d630018076c76",
    "classNotesCode": "4870b015-bc3e-4b05-9757-b2b15251f67b.pdf",
    "dppsPdfCode": "",
    "dppsSolutionCode": ""
  },
  {
    "lectureNumber": 38,
    "lectureName": "Hydrocarbons 01 : NCERT Back Exercise...",
    "lectureCode": "54af4dd3-d57b-40ef-a5b7-155d4c9d5189",
    "extId": "65a25d16c29bcd0018dbf8ed",
    "key": "6458bcc2a2e6e20018fb769d",
    "classNotesCode": "03a846a1-d6a8-4b24-949c-0c468faa33e5.pdf",
    "dppsPdfCode": "",
    "dppsSolutionCode": ""
  },
  {
    "lectureNumber": 39,
    "lectureName": "Biotechnology and its Application-01 ...",
    "lectureCode": "cd32b62f-6905-4005-a2a6-9d5c02f0aec1",
    "extId": "65a40cfdb8a03800182c4560",
    "key": "6458c667c2ebc80018533f1d",
    "classNotesCode": "5bcde3b6-e26f-44dd-8a28-3702a96e6744.pdf",
    "dppsPdfCode": "",
    "dppsSolutionCode": ""
  },
  {
    "lectureNumber": 40,
    "lectureName": "Principles of Inheritance and Variati...",
    "lectureCode": "7432bff4-4e1a-4a9d-a63d-77e0017dc195",
    "extId": "65bcc80c65022d0019855b76",
    "key": "6458c5a2c2ebc80018533e76",
    "classNotesCode": "51cdc479-2d14-4d04-86aa-e1f0ae64d7f8.pdf",
    "dppsPdfCode": "",
    "dppsSolutionCode": ""
  },
  {
    "lectureNumber": 41,
    "lectureName": "Principles of Inheritance and Variati...",
    "lectureCode": "8bf88c51-9e98-44e3-b8c6-859afc18599d",
    "extId": "65bcc764abfd13001828dbef",
    "key": "6458c64ba2e6e20018fb7e12",
    "classNotesCode": "f17296f0-7cc7-4ae1-a321-56d19990fd32.pdf",
    "dppsPdfCode": "",
    "dppsSolutionCode": ""
  },
  {
    "lectureNumber": 42,
    "lectureName": "Alcohol, Phenol And Ether 01 : NCERT ...",
    "lectureCode": "98b675eb-fdbe-47bc-bc53-4bc28aa68f87",
    "extId": "65b884e8c3e0920018bc5910",
    "key": "6458b787fb563800188e62ca",
    "classNotesCode": "5bcde3b6-e26f-44dd-8a28-3702a96e6744.pdf",
    "dppsPdfCode": "",
    "dppsSolutionCode": ""
  },
  {
    "lectureNumber": 43,
    "lectureName": "Alcohol, Phenol And Ether 02 : NCERT ...",
    "lectureCode": "77994e93-ba0f-4a79-bfc3-896bf87d460e",
    "extId": "65b885325d1276001847fb86",
    "key": "6458ba751610aa00184c451e",
    "classNotesCode": "51cdc479-2d14-4d04-86aa-e1f0ae64d7f8.pdf",
    "dppsPdfCode": "",
    "dppsSolutionCode": ""
  },
  {
    "lectureNumber": 44,
    "lectureName": "Cell: The Unit of Life : Ncert Discus...",
    "lectureCode": "a285526e-f834-4ab9-9a4f-6eb5251e3a1d",
    "extId": "64a9323df01c4000185caff7",
    "key": "64a90b68ee30870018a2d5fd",
    "classNotesCode": "f17296f0-7cc7-4ae1-a321-56d19990fd32.pdf",
    "dppsPdfCode": "",
    "dppsSolutionCode": ""
  },
  {
    "lectureNumber": 45,
    "lectureName": "The Living World : NCERT Discussion",
    "lectureCode": "40fb01c1-ee78-4b5d-8de1-86e73a515ace",
    "extId": "64847ed381c5f50019c6432a",
    "key": "648470d428127a001814c8ad",
    "classNotesCode": "27384b41-ef3a-484b-ba83-be7674bbdd0c.pdf",
    "dppsPdfCode": "",
    "dppsSolutionCode": ""
  },
  {
    "lectureNumber": 46,
    "lectureName": "back",
    "lectureCode": "04ae7709-9713-427d-a8e2-e2831e70d34e",
    "extId": "65c627133ba2310018b622ef",
    "key": "65c4762826964f0018a6c202",
    "classNotesCode": "22807a89-efed-4b9c-be7c-15472f026bd0.pdf",
    "dppsPdfCode": "",
    "dppsSolutionCode": ""
  },
  {
    "lectureNumber": 47,
    "lectureName": "first",
    "lectureCode": "9e24c4a6-967a-4093-bab2-dd1768eac7ed",
    "extId": "65c626d891b30f0018372195",
    "key": "65c477983aeeaa0018b7b32f",
    "classNotesCode": "a94cb211-1fc4-4af5-8929-846da0237787.pdf",
    "dppsPdfCode": "",
    "dppsSolutionCode": ""
  },
  {
    "lectureNumber": 48,
    "lectureName": "Amines 01 : Theory Session (Only Video)",
    "lectureCode": "77650010-9948-4753-89cf-9695edddc9da",
    "extId": "65cb10f222d6b80018dad259",
    "key": "65cb516c43242b001811af49",
    "classNotesCode": "11a7e6e7-eaa7-4060-8d4d-2c05d4ffaf0e.pdf",
    "dppsPdfCode": "",
    "dppsSolutionCode": ""
  },
  {
    "lectureNumber": 49,
    "lectureName": "back",
    "lectureCode": "c9a1bfeb-7207-49cb-8d5b-5bbc8313061e",
    "extId": "65d48f43c98bae0018af3733",
    "key": "65d3952cc72a99001822b37f",
    "classNotesCode": "42ea23b7-ebf9-451c-937c-ade4744201e6.pdf",
    "dppsPdfCode": "",
    "dppsSolutionCode": ""
  },
  {
    "lectureNumber": 50,
    "lectureName": "theory",
    "lectureCode": "4c9290dd-93d7-4551-abaa-6eb6d87117a2",
    "extId": "65d48ef400dcea0018afbc5e",
    "key": "65d396828364a30018183916",
    "classNotesCode": "",
    "dppsPdfCode": "",
    "dppsSolutionCode": ""
  }
]