[
{
        "lectureName": "Biotechnology 01 : Principles and Processes || No DPP",
        "lectureCode": "91f454ec-cb3d-450b-995f-98340531a966",
        "classNotesCode": "",
        "dppsPdfCode": ""
    },
    {
        "lectureName": "Biotechnology 02 : Applications || No DPP",
        "lectureCode": "eb78abeb-4cd8-4ca1-9d22-447ef0e1a21a",
        "classNotesCode": "",
        "dppsPdfCode": ""
    },
    {
        "lectureName": "Biotechnology 03 : Transgenic Animals",
        "lectureCode": "d0a6fef0-891b-4b22-a8ea-b1aecfe72c1e",
        "classNotesCode": "",
        "dppsPdfCode": ""
    },
    {
        "lectureName": "Biotechnology 04 : DPP Discussion",
        "lectureCode": "80367039-0a1c-4c35-8063-d563ab1acd5d",
        "classNotesCode": "",
        "dppsPdfCode": ""
    }
]