[
  {
    "lectureNumber": 1,
    "lectureName": "Non-Traditional Machining Method 06 :...",
    "lectureCode": "7c8c3114-9479-4bcb-8a83-f194aa23573c",
    "extId": "64f236a0fb60a60018121f67",
    "key": "64f608e3f8606600187dac08",
    "classNotesCode": "a4bd441d-9d97-4bd9-bc61-9c788e2068df.pdf",
    "dppsPdfCode": "7be31d60-e902-4a03-ae29-3c62e837e8ce.pdf",
    "dppsSolutionCode": ""
  },
  {
    "lectureNumber": 2,
    "lectureName": "Non-Traditional Machining Method 05 :...",
    "lectureCode": "3f6e2531-1ee4-4f72-bf91-c9dbf77ad552",
    "extId": "64f2368400ae29001859627f",
    "key": "64f5f77a009ab00019673765",
    "classNotesCode": "0b3c6dd9-599e-415f-bdcb-bb495bd0a13e.pdf",
    "dppsPdfCode": "769d7857-6338-455d-8f27-7776a8d6942a.pdf",
    "dppsSolutionCode": ""
  },
  {
    "lectureNumber": 3,
    "lectureName": "Non-Traditional Machining Method 04 :...",
    "lectureCode": "9f6605f8-6a93-4d3f-89cb-cbb175488b85",
    "extId": "64f0eea24fd94a0018c5ef42",
    "key": "64f21c14da63080019968bb1",
    "classNotesCode": "1d45d5ba-dcfa-46a3-9ab5-6cee34626a36.pdf",
    "dppsPdfCode": "b935276f-05e3-4e66-bb42-d89f52a4f3fa.pdf",
    "dppsSolutionCode": ""
  },
  {
    "lectureNumber": 4,
    "lectureName": "Non-Traditional Machining Method 03 :...",
    "lectureCode": "2fd31627-cfb1-4c71-8912-9e1a58ccc791",
    "extId": "64f0ee744fd94a0018c5ef2d",
    "key": "64f2016a65e83900181895e8",
    "classNotesCode": "9ce55b9c-7489-4a1e-ae9a-7893da84c5d8.pdf",
    "dppsPdfCode": "e564fd5f-9b64-4107-bb76-dee3e60bdfb5.pdf",
    "dppsSolutionCode": ""
  },
  {
    "lectureNumber": 5,
    "lectureName": "Non-Traditional Machining Method 02 :...",
    "lectureCode": "1a003d32-88b3-42d8-b3d6-4810150c108e",
    "extId": "64ef99778efe4600187012f6",
    "key": "64f0d1c4bd78cc0018bd72c3",
    "classNotesCode": "547a3d0d-e0ad-4314-9ce3-a817b199f138.pdf",
    "dppsPdfCode": "",
    "dppsSolutionCode": ""
  },
  {
    "lectureNumber": 6,
    "lectureName": "Non-Traditional Machining Method 01 :...",
    "lectureCode": "b99c5a81-335a-42eb-83ec-b8f42dd974f7",
    "extId": "64ef995972172b0018823ade",
    "key": "64f0b31d8d7e45001849b8e4",
    "classNotesCode": "9a7eaa3c-70fa-4cc0-b21e-3a058497bc76.pdf",
    "dppsPdfCode": "",
    "dppsSolutionCode": ""
  },
  {
    "lectureNumber": 7,
    "lectureName": "Non-Traditional Machining Method DPP Discussion...",
    "lectureCode": "",
    "extId": "",
    "key": "",
    "classNotesCode": "7be31d60-e902-4a03-ae29-3c62e837e8ce.pdf",
    "dppsPdfCode": "",
    "dppsSolutionCode": ""
  },
  {
    "lectureNumber": 8,
    "lectureName": "Non-Traditional Machining Method DPP Discussion...",
    "lectureCode": "",
    "extId": "",
    "key": "",
    "classNotesCode": "769d7857-6338-455d-8f27-7776a8d6942a.pdf",
    "dppsPdfCode": "",
    "dppsSolutionCode": ""
  }
]